setup.py
distributions_dsnd_pa/Binomialdistribution.py
distributions_dsnd_pa/Gaussiandistribution.py
distributions_dsnd_pa/Generaldistribution.py
distributions_dsnd_pa/__init__.py
distributions_dsnd_pa.egg-info/PKG-INFO
distributions_dsnd_pa.egg-info/SOURCES.txt
distributions_dsnd_pa.egg-info/dependency_links.txt
distributions_dsnd_pa.egg-info/not-zip-safe
distributions_dsnd_pa.egg-info/top_level.txt