Metadata-Version: 1.0
Name: distributions-dsnd-pa
Version: 0.1
Summary: Gaussian amd Binomial distributions
Home-page: UNKNOWN
Author: UNKNOWN
Author-email: UNKNOWN
License: UNKNOWN
Platform: UNKNOWN
